{
  "db_name": "SQLite",
  "query": "SELECT id, workflow_def_id, project_id, status, context, version, created_at, updated_at FROM workflow_run WHERE status IN ('pending', 'running')",
  "describe": {
    "columns": [
      {
        "name": "id",
        "ordinal": 0,
        "type_info": "Text"
      },
      {
        "name": "workflow_def_id",
        "ordinal": 1,
        "type_info": "Text"
      },
      {
        "name": "project_id",
        "ordinal": 2,
        "type_info": "Text"
      },
      {
        "name": "status",
        "ordinal": 3,
        "type_info": "Text"
      },
      {
        "name": "context",
        "ordinal": 4,
        "type_info": "Text"
      },
      {
        "name": "version",
        "ordinal": 5,
        "type_info": "Int64"
      },
      {
        "name": "created_at",
        "ordinal": 6,
        "type_info": "Text"
      },
      {
        "name": "updated_at",
        "ordinal": 7,
        "type_info": "Text"
      }
    ],
    "parameters": {
      "Right": 0
    },
    "nullable": [
      false,
      false,
      true,
      false,
      true,
      false,
      false,
      false
    ]
  },
  "hash": "335ea0362ac37f2843d54507e75c3ec14bbb3c20ea4a66f82721ffbd83a12bcb"
}
